cagen/__init__.py
cagen/cmd.py
cagen/libcagen.py
cagen/templates/list.md.tmpl
cagen/templates/list.md.tmpl.license
cagen/templates/schema.tmpl
cagen/templates/schema.tmpl.license
cagen-0.1.0.post3.dist-info/METADATA
cagen-0.1.0.post3.dist-info/WHEEL
cagen-0.1.0.post3.dist-info/entry_points.txt
cagen-0.1.0.post3.dist-info/top_level.txt
cagen-0.1.0.post3.dist-info/RECORD
