Metadata-Version: 2.1
Name: cagen
Version: 0.1.0.post3
Summary: A static site generator for cmpalgorithms project
Author: Xavier B.
Project-URL: Homepage, https://sr.ht/~somenxavierb/cagen/
Project-URL: Bug Tracker, https://todo.sr.ht/~somenxavierb/cagen-tasks
Project-URL: Repository, https://git.sr.ht/~somenxavierb/cagen
Project-URL: API Documentation, https://somenxavierb.srht.site/cagen/
Classifier: Development Status :: 3 - Alpha
Classifier: Environment :: Console
Classifier: Intended Audience :: Developers
Classifier: License :: OSI Approved :: GNU General Public License v2 (GPLv2)
Classifier: Natural Language :: English
Classifier: Operating System :: POSIX :: Linux
Classifier: Programming Language :: Python
Classifier: Programming Language :: Python :: 3
Classifier: Programming Language :: Python :: 3.10
Classifier: Topic :: Internet :: WWW/HTTP :: Site Management
Requires-Python: >=3.10
Requires-Dist: python-frontmatter (>=1.0.0)
Requires-Dist: pypandoc (>=1.10)
Requires-Dist: Mako (>=1.2.4)
